{
  "id": "acr-fasting-d096a9",
  "title": "Fasting Prior to IV Contrast | ACR Contrast Manual",
  "source": "acr-fasting.html",
  "blocks": [
    {
      "type": "paragraph",
      "text": "Auto-extracted from acr_contrast.docx. Verify locally against the official manual for clinical use."
    },
    {
      "type": "heading",
      "level": 2,
      "text": "Full Text"
    },
    {
      "type": "paragraph",
      "text": "Section: Fasting Prior to Intravascular Contrast Media Administration"
    }
  ]
}
