{
  "id": "downloaded-articles-downloaded-articles-converted-s00247-025-06335-x-32850a",
  "title": "s00247-025-06335-x",
  "source": "downloaded_articles/downloaded_articles/converted-s00247-025-06335-x.html",
  "blocks": [
    {
      "type": "image",
      "assetId": "asset_737e673219",
      "alt": "s00247-025-06335-x page 1"
    },
    {
      "type": "image",
      "assetId": "asset_a8cf231bf3",
      "alt": "s00247-025-06335-x page 2"
    },
    {
      "type": "image",
      "assetId": "asset_a705c52ff7",
      "alt": "s00247-025-06335-x page 3"
    },
    {
      "type": "image",
      "assetId": "asset_79ff8a0445",
      "alt": "s00247-025-06335-x page 4"
    },
    {
      "type": "image",
      "assetId": "asset_14f0d18004",
      "alt": "s00247-025-06335-x page 5"
    },
    {
      "type": "image",
      "assetId": "asset_4d25a08e7c",
      "alt": "s00247-025-06335-x page 6"
    },
    {
      "type": "image",
      "assetId": "asset_de9a4f3c5c",
      "alt": "s00247-025-06335-x page 7"
    },
    {
      "type": "image",
      "assetId": "asset_c16c8449d6",
      "alt": "s00247-025-06335-x page 8"
    },
    {
      "type": "image",
      "assetId": "asset_49da723c6f",
      "alt": "s00247-025-06335-x page 9"
    },
    {
      "type": "image",
      "assetId": "asset_19725f563e",
      "alt": "s00247-025-06335-x page 10"
    },
    {
      "type": "image",
      "assetId": "asset_1d3b0b7bfa",
      "alt": "s00247-025-06335-x page 11"
    },
    {
      "type": "image",
      "assetId": "asset_0ba3c69314",
      "alt": "s00247-025-06335-x page 12"
    },
    {
      "type": "image",
      "assetId": "asset_cb1db31c59",
      "alt": "s00247-025-06335-x page 13"
    },
    {
      "type": "image",
      "assetId": "asset_907550de9e",
      "alt": "s00247-025-06335-x page 14"
    },
    {
      "type": "image",
      "assetId": "asset_5630d1b2b5",
      "alt": "s00247-025-06335-x page 15"
    },
    {
      "type": "image",
      "assetId": "asset_fd17371b85",
      "alt": "s00247-025-06335-x page 16"
    }
  ]
}
