{
  "id": "protocols-chest-54a9dd",
  "title": "Chest & Cardiac MRI Protocols",
  "source": "protocols-chest.html",
  "blocks": [
    {
      "type": "paragraph",
      "text": "High-DPI PNG renders from chest and cardiac protocol PDFs."
    },
    {
      "type": "heading",
      "level": 2,
      "text": "MRA MRV CHEST WO CONTRAST"
    },
    {
      "type": "paragraph",
      "text": "5 pages - 300 DPI PNG"
    },
    {
      "type": "image",
      "assetId": "asset_protocols_chest_001",
      "alt": "MRA MRV CHEST WO CONTRAST - Page 1"
    },
    {
      "type": "image",
      "assetId": "asset_protocols_chest_002",
      "alt": "MRA MRV CHEST WO CONTRAST - Page 2"
    },
    {
      "type": "image",
      "assetId": "asset_protocols_chest_003",
      "alt": "MRA MRV CHEST WO CONTRAST - Page 3"
    },
    {
      "type": "image",
      "assetId": "asset_protocols_chest_004",
      "alt": "MRA MRV CHEST WO CONTRAST - Page 4"
    },
    {
      "type": "image",
      "assetId": "asset_protocols_chest_005",
      "alt": "MRA MRV CHEST WO CONTRAST - Page 5"
    },
    {
      "type": "heading",
      "level": 2,
      "text": "MRA MRV CHEST W - WO CONTRAST"
    },
    {
      "type": "paragraph",
      "text": "6 pages - 300 DPI PNG"
    },
    {
      "type": "image",
      "assetId": "asset_protocols_chest_006",
      "alt": "MRA MRV CHEST W - WO CONTRAST - Page 1"
    },
    {
      "type": "image",
      "assetId": "asset_protocols_chest_007",
      "alt": "MRA MRV CHEST W - WO CONTRAST - Page 2"
    },
    {
      "type": "image",
      "assetId": "asset_protocols_chest_008",
      "alt": "MRA MRV CHEST W - WO CONTRAST - Page 3"
    },
    {
      "type": "image",
      "assetId": "asset_protocols_chest_009",
      "alt": "MRA MRV CHEST W - WO CONTRAST - Page 4"
    },
    {
      "type": "image",
      "assetId": "asset_protocols_chest_010",
      "alt": "MRA MRV CHEST W - WO CONTRAST - Page 5"
    },
    {
      "type": "image",
      "assetId": "asset_protocols_chest_011",
      "alt": "MRA MRV CHEST W - WO CONTRAST - Page 6"
    },
    {
      "type": "heading",
      "level": 2,
      "text": "MRI CARDIAC FOR AMYLOIDOSIS"
    },
    {
      "type": "paragraph",
      "text": "2 pages - 300 DPI PNG"
    },
    {
      "type": "image",
      "assetId": "asset_protocols_chest_012",
      "alt": "MRI CARDIAC FOR AMYLOIDOSIS - Page 1"
    },
    {
      "type": "image",
      "assetId": "asset_protocols_chest_013",
      "alt": "MRI CARDIAC FOR AMYLOIDOSIS - Page 2"
    },
    {
      "type": "heading",
      "level": 2,
      "text": "MRI CARDIAC FOR ARVD"
    },
    {
      "type": "paragraph",
      "text": "2 pages - 300 DPI PNG"
    },
    {
      "type": "image",
      "assetId": "asset_protocols_chest_014",
      "alt": "MRI CARDIAC FOR ARVD - Page 1"
    },
    {
      "type": "image",
      "assetId": "asset_protocols_chest_015",
      "alt": "MRI CARDIAC FOR ARVD - Page 2"
    },
    {
      "type": "heading",
      "level": 2,
      "text": "MRI CARDIAC FOR CONGENITAL HEART DISEASE, ASD-VSD"
    },
    {
      "type": "paragraph",
      "text": "2 pages - 300 DPI PNG"
    },
    {
      "type": "image",
      "assetId": "asset_protocols_chest_016",
      "alt": "MRI CARDIAC FOR CONGENITAL HEART DISEASE, ASD-VSD - Page 1"
    },
    {
      "type": "image",
      "assetId": "asset_protocols_chest_017",
      "alt": "MRI CARDIAC FOR CONGENITAL HEART DISEASE, ASD-VSD - Page 2"
    },
    {
      "type": "heading",
      "level": 2,
      "text": "MRI CARDIAC FOR MASS"
    },
    {
      "type": "paragraph",
      "text": "2 pages - 300 DPI PNG"
    },
    {
      "type": "image",
      "assetId": "asset_protocols_chest_018",
      "alt": "MRI CARDIAC FOR MASS - Page 1"
    },
    {
      "type": "image",
      "assetId": "asset_protocols_chest_019",
      "alt": "MRI CARDIAC FOR MASS - Page 2"
    },
    {
      "type": "heading",
      "level": 2,
      "text": "MRI CARDIAC FOR PERICARDITIS"
    },
    {
      "type": "paragraph",
      "text": "2 pages - 300 DPI PNG"
    },
    {
      "type": "image",
      "assetId": "asset_protocols_chest_020",
      "alt": "MRI CARDIAC FOR PERICARDITIS - Page 1"
    },
    {
      "type": "image",
      "assetId": "asset_protocols_chest_021",
      "alt": "MRI CARDIAC FOR PERICARDITIS - Page 2"
    },
    {
      "type": "heading",
      "level": 2,
      "text": "MRI CARDIAC STANDARD"
    },
    {
      "type": "paragraph",
      "text": "2 pages - 300 DPI PNG"
    },
    {
      "type": "image",
      "assetId": "asset_protocols_chest_022",
      "alt": "MRI CARDIAC STANDARD - Page 1"
    },
    {
      "type": "image",
      "assetId": "asset_protocols_chest_023",
      "alt": "MRI CARDIAC STANDARD - Page 2"
    },
    {
      "type": "heading",
      "level": 2,
      "text": "MRI CARDIAC WITH MRA CHEST"
    },
    {
      "type": "paragraph",
      "text": "2 pages - 300 DPI PNG"
    },
    {
      "type": "image",
      "assetId": "asset_protocols_chest_024",
      "alt": "MRI CARDIAC WITH MRA CHEST - Page 1"
    },
    {
      "type": "image",
      "assetId": "asset_protocols_chest_025",
      "alt": "MRI CARDIAC WITH MRA CHEST - Page 2"
    },
    {
      "type": "heading",
      "level": 2,
      "text": "MRI CHEST FOR MASS WO OR W-WO CONTRAST"
    },
    {
      "type": "paragraph",
      "text": "2 pages - 300 DPI PNG"
    },
    {
      "type": "image",
      "assetId": "asset_protocols_chest_026",
      "alt": "MRI CHEST FOR MASS WO OR W-WO CONTRAST - Page 1"
    },
    {
      "type": "image",
      "assetId": "asset_protocols_chest_027",
      "alt": "MRI CHEST FOR MASS WO OR W-WO CONTRAST - Page 2"
    },
    {
      "type": "heading",
      "level": 2,
      "text": "MRI CHEST FOR THYMUS WO OR W-WO CONTRAST"
    },
    {
      "type": "paragraph",
      "text": "2 pages - 300 DPI PNG"
    },
    {
      "type": "image",
      "assetId": "asset_protocols_chest_028",
      "alt": "MRI CHEST FOR THYMUS WO OR W-WO CONTRAST - Page 1"
    },
    {
      "type": "image",
      "assetId": "asset_protocols_chest_029",
      "alt": "MRI CHEST FOR THYMUS WO OR W-WO CONTRAST - Page 2"
    }
  ]
}
